shellchat_Lhgrandgtr/__init__.py
shellchat_Lhgrandgtr/main.py
shellchat_Lhgrandgtr-1.0.5.dist-info/METADATA
shellchat_Lhgrandgtr-1.0.5.dist-info/WHEEL
shellchat_Lhgrandgtr-1.0.5.dist-info/entry_points.txt
shellchat_Lhgrandgtr-1.0.5.dist-info/top_level.txt
shellchat_Lhgrandgtr-1.0.5.dist-info/RECORD
