Metadata-Version: 2.1
Name: shellchat-Lhgrandgtr
Version: 1.0.5
Summary: UNKNOWN
Home-page: UNKNOWN
License: UNKNOWN
Platform: UNKNOWN
Requires-Dist: deprecated
Requires-Dist: prompt-toolkit
Requires-Dist: requests
